emissionsapi_worldmap_creator/__init__.py
emissionsapi_worldmap_creator/__main__.py
emissionsapi_worldmap_creator-0.2.dist-info/METADATA
emissionsapi_worldmap_creator-0.2.dist-info/WHEEL
emissionsapi_worldmap_creator-0.2.dist-info/entry_points.txt
emissionsapi_worldmap_creator-0.2.dist-info/top_level.txt
emissionsapi_worldmap_creator-0.2.dist-info/RECORD
