Metadata-Version: 2.1
Name: emissionsapi-worldmap-creator
Version: 0.2
Summary: Emissions API's World Map image creator
Home-page: https://github.com/emissions-api/emissionsapi-worldmap-creator
Author: Emissions API Developers
License: MIT
Platform: UNKNOWN
Classifier: Development Status :: 4 - Beta
Classifier: Environment :: Console
Classifier: Framework :: Matplotlib
Classifier: Intended Audience :: Science/Research
Classifier: License :: OSI Approved :: MIT License
Classifier: Natural Language :: English
Classifier: Programming Language :: Python :: 3
Classifier: Programming Language :: Python :: 3 :: Only
Classifier: Topic :: Scientific/Engineering :: GIS
Classifier: Topic :: Scientific/Engineering :: Visualization
Requires-Dist: geopandas
Requires-Dist: h3
Requires-Dist: matplotlib
Requires-Dist: descartes
